Metadata-Version: 2.1
Name: auto-translation
Version: 0.1.5
Summary: A simple python library used to translate and speak a given text from the user with Google Translation using user's Chrome browser. 
Home-page: https://github.com/mouh2020/auto-translation
Author: Mohammed BADI
Author-email: badimohammed2019@gmail.com
License: UNKNOWN
Keywords: translation,traduction,translate,speech,voice,google translation,languages
Platform: UNKNOWN
Classifier: Intended Audience :: Education
Classifier: Natural Language :: English
Classifier: Operating System :: Microsoft :: Windows
Classifier: Programming Language :: Python
Classifier: Topic :: Multimedia :: Sound/Audio
Classifier: Topic :: Multimedia :: Sound/Audio :: Speech
Classifier: Topic :: Software Development :: Libraries :: Python Modules
Classifier: Topic :: Communications :: Chat
